django_email_queue/__init__.py
django_email_queue/admin.py
django_email_queue/app_settings.py
django_email_queue/apps.py
django_email_queue/backends.py
django_email_queue/models.py
django_email_queue/worker.py
django_email_queue/locales/.gitignore
django_email_queue/locales/babel.cfg
django_email_queue/management/__init__.py
django_email_queue/management/commands/__init__.py
django_email_queue/management/commands/delete_sent_queued_messages.py
django_email_queue/management/commands/send_queued_messages.py
django_email_queue/migrations/0001_initial.py
django_email_queue/migrations/0002_auto_20180412_1413.py
django_email_queue/migrations/0003_auto_20180504_0956.py
django_email_queue/migrations/__init__.py
django_email_queue-0.23.0.dist-info/DESCRIPTION.rst
django_email_queue-0.23.0.dist-info/METADATA
django_email_queue-0.23.0.dist-info/RECORD
django_email_queue-0.23.0.dist-info/WHEEL
django_email_queue-0.23.0.dist-info/entry_points.txt
django_email_queue-0.23.0.dist-info/metadata.json
django_email_queue-0.23.0.dist-info/top_level.txt
