Metadata-Version: 2.0
Name: django-email-queue
Version: 0.23.0
Summary: Queening and storing EMAIL_BACKEND for django.
Home-page: https://github.com/wooyek/django-email-queue
Author: Janusz Skonieczny
Author-email: js+pypi@bravelabs.pl
License: UNKNOWN
Keywords: django-email-queue
Platform: UNKNOWN
Classifier: Development Status :: 4 - Beta
Classifier: Framework :: Django :: 1.10
Classifier: Intended Audience :: Developers
Classifier: Environment :: Web Environment
Classifier: Natural Language :: English
Classifier: Programming Language :: Python :: 2
Classifier: Programming Language :: Python :: 2.7
Classifier: Programming Language :: Python :: 3
Classifier: Programming Language :: Python :: 3.4
Classifier: Programming Language :: Python :: 3.5
Classifier: Programming Language :: Python :: 3.6
Classifier: Programming Language :: Python :: 3.7
Requires-Python: >=2.7
Provides-Extra: factories
Requires-Dist: django (>=1.8)
Provides-Extra: factories
Requires-Dist: factory-boy; extra == 'factories'
